stisblazefix/__init__.py
stisblazefix/_version.py
stisblazefix/stisblazefix.py
stisblazefix/test_sbf.py
stisblazefix-1.2.0.dist-info/licenses/LICENSE.txt
stisblazefix-1.2.0.dist-info/METADATA
stisblazefix-1.2.0.dist-info/WHEEL
stisblazefix-1.2.0.dist-info/top_level.txt
stisblazefix-1.2.0.dist-info/RECORD
