Metadata-Version: 2.4
Name: stisblazefix
Version: 1.2.0
Summary: HST/STIS echelle blaze function correction
Author: M. Baer, C. Proffitt
Maintainer: Sean Lockwood
License: Copyright (C) 2017-2025 Association of Universities for Research in Astronomy (AURA)
Project-URL: Homepage, https://www.stsci.edu/hst/instrumentation/stis
Project-URL: Support, https://hsthelp.stsci.edu
Keywords: astronomy
Classifier: Programming Language :: Python
Classifier: Programming Language :: Python :: 3.9
Classifier: Programming Language :: Python :: 3.10
Classifier: Programming Language :: Python :: 3.11
Classifier: Programming Language :: Python :: 3.12
Classifier: Development Status :: 5 - Production/Stable
Classifier: Operating System :: OS Independent
Classifier: Intended Audience :: Science/Research
Classifier: License :: OSI Approved :: BSD License
Classifier: Topic :: Scientific/Engineering :: Astronomy
Classifier: Topic :: Scientific/Engineering :: Physics
Classifier: Topic :: Software Development :: Libraries :: Python Modules
Requires-Python: >=3.9
License-File: LICENSE.txt
Requires-Dist: numpy>=1.13
Requires-Dist: scipy
Requires-Dist: astropy
Requires-Dist: matplotlib
Requires-Dist: lmfit
Provides-Extra: docs
Requires-Dist: sphinx; extra == "docs"
Provides-Extra: test
Requires-Dist: pytest; extra == "test"
Requires-Dist: pytest-cov; extra == "test"
Dynamic: license-file
